stateInfo/__init__.py
stateInfo/stateInfo.py
stateInfo-0.0.3.dist-info/LICENSE
stateInfo-0.0.3.dist-info/METADATA
stateInfo-0.0.3.dist-info/WHEEL
stateInfo-0.0.3.dist-info/top_level.txt
stateInfo-0.0.3.dist-info/RECORD
