Metadata-Version: 2.1
Name: stateInfo
Version: 0.0.3
Summary: Get capital city and state language of Indian States
Author: RohitS
Author-email: rohitsanadi08@gmail.com
License: UNKNOWN
Keywords: python,state,capital,language
Platform: UNKNOWN
Classifier: Development Status :: 1 - Planning
Classifier: Intended Audience :: Developers
Classifier: Programming Language :: Python :: 3
Classifier: Operating System :: Unix
Classifier: Operating System :: MacOS :: MacOS X
Classifier: Operating System :: Microsoft :: Windows
License-File: LICENSE
